{
    "version": 1,
    "license": "CC-BY-SA-3.0",
    "copyright": "Created by Valithor for Space Station 14",
    "size": {
    "x": 32,
    "y": 32
    },
    "states": [
    {
        "name": "full"
    },
    {
        "name": "tent0",
        "directions": 4
    },
    {
        "name": "tent1",
        "directions": 4
    },
    {
        "name": "tent2",
        "directions": 4
    },
    {
        "name": "tent3",
        "directions": 4
    },
    {
        "name": "tent4",
        "directions": 4
    },
    {
        "name": "tent5",
        "directions": 4
    },
    {
        "name": "tent6",
        "directions": 4
    },
    {
        "name": "tent7",
        "directions": 4
    }
    ]
}